appligen/__init__.py
appligen/admin.py
appligen/apps.py
appligen/cli.py
appligen/generator.py
appligen/models.py
appligen/run.py
appligen/tests.py
appligen/views.py
appligen/migrations/__init__.py
envgen/__init__.py
envgen/admin.py
envgen/apps.py
envgen/cli.py
envgen/models.py
envgen/tests.py
envgen/views.py
envgen/migrations/__init__.py
todo_app/__init__.py
todo_app/admin.py
todo_app/apps.py
todo_app/forms.py
todo_app/models.py
todo_app/tests.py
todo_app/urls.py
todo_app/views.py
todo_app/migrations/0001_initial.py
todo_app/migrations/__init__.py
todo_app/templates/todo_app/delete.html
todo_app/templates/todo_app/form.html
todo_app/templates/todo_app/list.html
jaysimy_todo_app-0.1.0.dist-info/METADATA
jaysimy_todo_app-0.1.0.dist-info/WHEEL
jaysimy_todo_app-0.1.0.dist-info/top_level.txt
jaysimy_todo_app-0.1.0.dist-info/RECORD
